gpxo/__init__.py
gpxo/general.py
gpxo/track.py
tests/test_gpxo.py
gpxo-0.2.0.dist-info/LICENSE
gpxo-0.2.0.dist-info/METADATA
gpxo-0.2.0.dist-info/WHEEL
gpxo-0.2.0.dist-info/top_level.txt
gpxo-0.2.0.dist-info/RECORD
