Metadata-Version: 2.2
Name: gpxo
Version: 0.2.0
Summary: Load, analyze and plot GPS data from GPX files with numpy/pandas
Author-email: Olivier Vincent <ovinc.py@gmail.com>
License: BSD 3-Clause License
Project-URL: Homepage, https://github.com/ovinc/gpxo
Project-URL: Documentation, https://github.com/ovinc/gpxo/README.md
Project-URL: Repository, https://github.com/ovinc/gpxo.git
Keywords: gps,gpx,numpy,pandas,plot,analyze,compass
Classifier: Programming Language :: Python :: 3
Classifier: Operating System :: OS Independent
Classifier: License :: OSI Approved :: BSD License
Requires-Python: >=3.6
License-File: LICENSE
Requires-Dist: pandas
Requires-Dist: numpy
Requires-Dist: matplotlib
Requires-Dist: vincenty
Requires-Dist: gpxpy
Requires-Dist: importlib-metadata
Provides-Extra: map
Requires-Dist: mplleaflet; extra == "map"
